{
	"info": {
		"_postman_id": "2ba2ff4c-0dbb-493b-9115-b4a52c5589b8",
		"name": "API Requests",
		"description": "Collection with all the possible API requests and all available endpoints.",
		"schema": "https://schema.getpostman.com/json/collection/v2.1.0/collection.json",
		"_uid": "28724924-2ba2ff4c-0dbb-493b-9115-b4a52c5589b8"
	},
	"item": [
		{
			"name": "Auth",
			"item": [
				{
					"name": "/login",
					"id": "e7623876-903f-476d-bd01-d238aea683c2",
					"protocolProfileBehavior": {
						"disableBodyPruning": true
					},
					"request": {
						"auth": {
							"type": "noauth"
						},
						"method": "POST",
						"header": [],
						"body": {
							"mode": "raw",
							"raw": "{\r\n    \"email\": \"grace.hopper@systers.xyz\",\r\n    \"password\": \"123456\"\r\n}",
							"options": {
								"raw": {
									"language": "json"
								}
							}
						},
						"url": {
							"raw": "https://burger-queen-api-mock-u59i-dev.fl0.io/login",
							"protocol": "https",
							"host": [
								"burger-queen-api-mock-u59i-dev",
								"fl0",
								"io"
							],
							"path": [
								"login"
							]
						}
					},
					"response": []
				}
			],
			"id": "da7eec78-230c-4e4b-8019-95b73c44aa58",
			"description": "Collection containing all the request for the login endpoint."
		},
		{
			"name": "Users",
			"item": [
				{
					"name": "/users",
					"id": "b7e47a3f-3ad7-4c3c-a760-82775063b787",
					"protocolProfileBehavior": {
						"disableBodyPruning": true
					},
					"request": {
						"method": "GET",
						"header": [],
						"url": {
							"raw": "https://burger-queen-api-mock-r47a.onrender.com/users?content-type: =application/json",
							"protocol": "https",
							"host": [
								"burger-queen-api-mock-r47a",
								"onrender",
								"com"
							],
							"path": [
								"users"
							],
							"query": [
								{
									"key": "content-type: ",
									"value": "application/json"
								}
							]
						}
					},
					"response": []
				},
				{
					"name": "/users",
					"id": "c3ea35e1-98f5-4f24-8b59-333b5aba5d73",
					"protocolProfileBehavior": {
						"disableBodyPruning": true
					},
					"request": {
						"method": "POST",
						"header": [],
						"body": {
							"mode": "raw",
							"raw": "{\r\n    \"email\": \"iamawaiter2@mail.com\",\r\n    \"password\": \"123456\",\r\n    \"role\": \"waiter\"\r\n}",
							"options": {
								"raw": {
									"language": "json"
								}
							}
						},
						"url": {
							"raw": "https://burger-queen-api-mock-r47a.onrender.com/users",
							"protocol": "https",
							"host": [
								"burger-queen-api-mock-r47a",
								"onrender",
								"com"
							],
							"path": [
								"users"
							]
						}
					},
					"response": []
				},
				{
					"name": "/users/{uid}",
					"id": "49d97874-033f-41b1-903b-7af5e5bd8102",
					"protocolProfileBehavior": {
						"disableBodyPruning": true
					},
					"request": {
						"method": "GET",
						"header": [],
						"body": {
							"mode": "raw",
							"raw": "",
							"options": {
								"raw": {
									"language": "json"
								}
							}
						},
						"url": {
							"raw": "https://burger-queen-api-mock-r47a.onrender.com/users/{id}",
							"protocol": "https",
							"host": [
								"burger-queen-api-mock-r47a",
								"onrender",
								"com"
							],
							"path": [
								"users",
								"{id}"
							]
						}
					},
					"response": []
				},
				{
					"name": "/users/{uid}",
					"id": "ad2aad31-fdbf-482f-b2fa-086289d2fa24",
					"protocolProfileBehavior": {
						"disableBodyPruning": true
					},
					"request": {
						"method": "PATCH",
						"header": [],
						"body": {
							"mode": "raw",
							"raw": "{\r\n    \"email\": \"iamawaiter2@mail.com\",\r\n    \"password\": \"123456\",\r\n    \"role\": \"waiter\"\r\n}",
							"options": {
								"raw": {
									"language": "json"
								}
							}
						},
						"url": {
							"raw": "https://burger-queen-api-mock-r47a.onrender.com/users/{id}",
							"protocol": "https",
							"host": [
								"burger-queen-api-mock-r47a",
								"onrender",
								"com"
							],
							"path": [
								"users",
								"{id}"
							]
						}
					},
					"response": []
				},
				{
					"name": "/users/{uid}",
					"id": "e246cb2d-66e5-4d0f-bcb1-b2c0d76a2d3b",
					"protocolProfileBehavior": {
						"disableBodyPruning": true
					},
					"request": {
						"method": "DELETE",
						"header": [],
						"body": {
							"mode": "raw",
							"raw": "{\r\n    \"email\": \"iamawaiter2@mail.com\",\r\n    \"password\": \"123456\",\r\n    \"role\": \"waiter\"\r\n}",
							"options": {
								"raw": {
									"language": "json"
								}
							}
						},
						"url": {
							"raw": "https://burger-queen-api-mock-r47a.onrender.com/users/{id}",
							"protocol": "https",
							"host": [
								"burger-queen-api-mock-r47a",
								"onrender",
								"com"
							],
							"path": [
								"users",
								"{id}"
							]
						}
					},
					"response": []
				}
			],
			"id": "47bfb7e8-884c-4464-8820-22ba05074841",
			"description": "Collection containing all the request for the users endpoint."
		},
		{
			"name": "Orders",
			"item": [
				{
					"name": "/orders",
					"id": "c14abbac-53f8-4263-bc61-4336629957e7",
					"protocolProfileBehavior": {
						"disableBodyPruning": true
					},
					"request": {
						"method": "GET",
						"header": [
							{
								"key": "Content-Type",
								"value": "application/json",
								"type": "text"
							}
						],
						"body": {
							"mode": "raw",
							"raw": "",
							"options": {
								"raw": {
									"language": "json"
								}
							}
						},
						"url": {
							"raw": "https://burger-queen-api-mock-u59i-dev.fl0.io/orders",
							"protocol": "https",
							"host": [
								"burger-queen-api-mock-u59i-dev",
								"fl0",
								"io"
							],
							"path": [
								"orders"
							]
						}
					},
					"response": []
				},
				{
					"name": "/orders",
					"id": "db370756-52e2-4553-8369-ec4ba01301ea",
					"protocolProfileBehavior": {
						"disableBodyPruning": true
					},
					"request": {
						"method": "POST",
						"header": [
							{
								"key": "Content-Type",
								"value": "application/json",
								"type": "text"
							}
						],
						"body": {
							"mode": "raw",
							"raw": "",
							"options": {
								"raw": {
									"language": "json"
								}
							}
						},
						"url": {
							"raw": "https://burger-queen-api-mock-r47a.onrender.com/orders",
							"protocol": "https",
							"host": [
								"burger-queen-api-mock-r47a",
								"onrender",
								"com"
							],
							"path": [
								"orders"
							]
						}
					},
					"response": []
				},
				{
					"name": "/orders/{orderId}",
					"id": "52a45cc1-361a-4650-9a75-f64b9d2ea29d",
					"protocolProfileBehavior": {
						"disableBodyPruning": true
					},
					"request": {
						"method": "GET",
						"header": [
							{
								"key": "Content-Type",
								"value": "application/json",
								"type": "text"
							}
						],
						"url": {
							"raw": "https://burger-queen-api-mock-r47a.onrender.com/orders/{id}",
							"protocol": "https",
							"host": [
								"burger-queen-api-mock-r47a",
								"onrender",
								"com"
							],
							"path": [
								"orders",
								"{id}"
							]
						}
					},
					"response": []
				},
				{
					"name": "/orders/{orderId}",
					"id": "5526bf85-d249-47b6-8339-5164dc677a8b",
					"protocolProfileBehavior": {
						"disableBodyPruning": true
					},
					"request": {
						"method": "PATCH",
						"header": [
							{
								"key": "Content-Type",
								"value": "application/json",
								"type": "text"
							}
						],
						"url": {
							"raw": "https://burger-queen-api-mock-r47a.onrender.com/orders/{id}",
							"protocol": "https",
							"host": [
								"burger-queen-api-mock-r47a",
								"onrender",
								"com"
							],
							"path": [
								"orders",
								"{id}"
							]
						}
					},
					"response": []
				},
				{
					"name": "/orders/{orderId}",
					"id": "cf27eac7-1ed9-475e-9516-53671d458555",
					"protocolProfileBehavior": {
						"disableBodyPruning": true
					},
					"request": {
						"method": "DELETE",
						"header": [],
						"body": {
							"mode": "raw",
							"raw": "{\r\n    \"email\": \"iamawaiter2@mail.com\",\r\n    \"password\": \"123456\",\r\n    \"role\": \"waiter\"\r\n}",
							"options": {
								"raw": {
									"language": "json"
								}
							}
						},
						"url": {
							"raw": "https://burger-queen-api-mock-r47a.onrender.com/orders/{orderId}",
							"protocol": "https",
							"host": [
								"burger-queen-api-mock-r47a",
								"onrender",
								"com"
							],
							"path": [
								"orders",
								"{orderId}"
							]
						}
					},
					"response": []
				}
			],
			"id": "9b9bc261-f1f7-4fec-a088-5f78afccc066",
			"description": "Collection containing all the request for the orders endpoint."
		},
		{
			"name": "Products",
			"item": [
				{
					"name": "/products",
					"id": "ff4deaf2-ac5e-4d0b-bebd-4e30b6dc71d0",
					"protocolProfileBehavior": {
						"disableBodyPruning": true
					},
					"request": {
						"method": "GET",
						"header": [],
						"body": {
							"mode": "raw",
							"raw": "",
							"options": {
								"raw": {
									"language": "json"
								}
							}
						},
						"url": {
							"raw": "https://burger-queen-api-mock-r47a.onrender.com/products",
							"protocol": "https",
							"host": [
								"burger-queen-api-mock-r47a",
								"onrender",
								"com"
							],
							"path": [
								"products"
							]
						}
					},
					"response": []
				},
				{
					"name": "/products",
					"id": "cbae4cc2-c22e-4f8c-80a8-da7082d7b6e1",
					"protocolProfileBehavior": {
						"disableBodyPruning": true
					},
					"request": {
						"method": "POST",
						"header": [],
						"body": {
							"mode": "raw",
							"raw": "",
							"options": {
								"raw": {
									"language": "json"
								}
							}
						},
						"url": {
							"raw": "https://burger-queen-api-mock-r47a.onrender.com/products",
							"protocol": "https",
							"host": [
								"burger-queen-api-mock-r47a",
								"onrender",
								"com"
							],
							"path": [
								"products"
							]
						}
					},
					"response": []
				},
				{
					"name": "/products/{productId}",
					"id": "1a9851d3-0b91-4186-b191-4c26a40a988f",
					"protocolProfileBehavior": {
						"disableBodyPruning": true
					},
					"request": {
						"method": "GET",
						"header": [],
						"body": {
							"mode": "raw",
							"raw": "",
							"options": {
								"raw": {
									"language": "json"
								}
							}
						},
						"url": {
							"raw": "https://burger-queen-api-mock-r47a.onrender.com/products/{productId}",
							"protocol": "https",
							"host": [
								"burger-queen-api-mock-r47a",
								"onrender",
								"com"
							],
							"path": [
								"products",
								"{productId}"
							]
						}
					},
					"response": []
				},
				{
					"name": "/products/{productId}",
					"id": "eec532b4-965f-4570-a75b-8764b97fddda",
					"protocolProfileBehavior": {
						"disableBodyPruning": true
					},
					"request": {
						"method": "PATCH",
						"header": [],
						"body": {
							"mode": "raw",
							"raw": "",
							"options": {
								"raw": {
									"language": "json"
								}
							}
						},
						"url": {
							"raw": "https://burger-queen-api-mock-r47a.onrender.com/products/{productId}",
							"protocol": "https",
							"host": [
								"burger-queen-api-mock-r47a",
								"onrender",
								"com"
							],
							"path": [
								"products",
								"{productId}"
							]
						}
					},
					"response": []
				},
				{
					"name": "/products/{productId}",
					"id": "3f1a88b9-ff95-4fc5-8fbf-422b7b4b3e46",
					"protocolProfileBehavior": {
						"disableBodyPruning": true
					},
					"request": {
						"method": "DELETE",
						"header": [],
						"body": {
							"mode": "raw",
							"raw": "",
							"options": {
								"raw": {
									"language": "json"
								}
							}
						},
						"url": {
							"raw": "https://burger-queen-api-mock-r47a.onrender.com/products/{productId}",
							"protocol": "https",
							"host": [
								"burger-queen-api-mock-r47a",
								"onrender",
								"com"
							],
							"path": [
								"products",
								"{productId}"
							]
						}
					},
					"response": []
				}
			],
			"id": "7fcc4f4d-9674-4f10-9fb5-93182175d099",
			"description": "Collection containing all the request for the products endpoint."
		}
	],
	"auth": {
		"type": "bearer"
	},
	"event": [
		{
			"listen": "prerequest",
			"script": {
				"id": "cab9cb0e-b82d-4bbb-9cc6-926d43d61c3a",
				"type": "text/javascript",
				"exec": [
					""
				]
			}
		},
		{
			"listen": "test",
			"script": {
				"id": "1c6dad03-f46d-4e0f-8fd7-bd711c9aa255",
				"type": "text/javascript",
				"exec": [
					""
				]
			}
		}
	]
}